readme_patcher/__init__.py
readme_patcher/badge.py
readme_patcher/config.py
readme_patcher/file.py
readme_patcher/filters.py
readme_patcher/functions.py
readme_patcher/github.py
readme_patcher/project.py
readme_patcher/py_project.py
readme_patcher/template.py
readme_patcher-0.7.2.dist-info/METADATA
readme_patcher-0.7.2.dist-info/WHEEL
readme_patcher-0.7.2.dist-info/entry_points.txt
readme_patcher-0.7.2.dist-info/licenses/LICENSE
readme_patcher-0.7.2.dist-info/RECORD
