Metadata-Version: 2.4
Name: readme_patcher
Version: 0.7.2
Summary: Generate README files from templates. Allow input from functions calls and cli output.
Project-URL: Repository, https://github.com/Josef-Friedrich/readme_patcher
Author-email: Josef Friedrich <josef@friedrich.rocks>
License: MIT
License-File: LICENSE
Classifier: License :: OSI Approved :: MIT License
Requires-Python: ~=3.8
Requires-Dist: jinja2<4,>=3
Requires-Dist: pyproject-parser<1,>=0
Requires-Dist: requests<3,>=2
Requires-Dist: types-requests<3,>=2
